D_flip_flop_test/vsrc/D_ff.v
//准确而言，本设计为直接验证触发器的特性，即当检测到数据时，并不会直接产生输出
//该模块为同步D触发器，即复位的时间其实是与时钟信号同步的；
//如果要得到异步D触发器，可以在敏感表里面添加进去negedge rst；
module  D_ff(
    clk,
    rst,
    d,
    q,
    q_o
);
    input clk;
    input rst;
    input d;

    output reg q;
    output reg q_o;

    always@(posedge clk)begin
        if(!rst)begin
              q <= 1'b0;
            q_o <= 1'b0; 
        end
        else begin
            q <= d;
            q_o <= ~d; 
        end          
    end


endmodule

D_flip_flop_test/waveform.vcd
$version Generated by VerilatedVcd $end
$date Sat Jan 14 16:09:10 2023 $end
$timescale 1ps $end

 $scope module TOP $end
  $var wire  1 # clk $end
  $var wire  1 % d $end
  $var wire  1 & q $end
  $var wire  1 ' q_o $end
  $var wire  1 $ rst $end
  $scope module D_ff $end
   $var wire  1 # clk $end
   $var wire  1 % d $end
   $var wire  1 & q $end
   $var wire  1 ' q_o $end
   $var wire  1 $ rst $end
  $upscope $end
 $upscope $end
$enddefinitions $end


#0
1#
1$
0%
0&
0'
#1
0#
#2
1#
1'
#3
0#
0$
#4
1#
0'
#5
0#
#6
1#
#7
0#
1$
#8
1#
1%
1'
#9
0#
#10
1#
1&
0'
#11
0#
#12
1#
0%
#13
0#
#14
1#
0&
1'
